pytokamap/__init__.py
pytokamap/api.py
pytokamap/mapper.py
pytokamap/mast.py
pytokamap/plugins.py
pytokamap/reader.py
pytokamap/transforms.py
pytokamap/types.py
pytokamap/writers.py
pytokamap-2024.0.0.dist-info/LICENSE
pytokamap-2024.0.0.dist-info/METADATA
pytokamap-2024.0.0.dist-info/WHEEL
pytokamap-2024.0.0.dist-info/top_level.txt
pytokamap-2024.0.0.dist-info/RECORD
