Metadata-Version: 2.1
Name: pytokamap
Version: 2024.0.0
Summary: A python library for mapping between Fusion data formats
Maintainer-email: Samuel Jackson <samuel.jackson@ukaea.uk>
Project-URL: Repository, https://github.com/samueljackson92/pytokamap.git
Project-URL: Bug Tracker, https://github.com/samueljackson92/pytokamap/issues
Classifier: Development Status :: 4 - Beta
Classifier: Programming Language :: Python
Requires-Python: >=3.9
License-File: LICENSE
Requires-Dist: netCDF4
Requires-Dist: Jinja2
Requires-Dist: pytest
Requires-Dist: xarray
Requires-Dist: zarr
Requires-Dist: dask
Requires-Dist: mkdocs
Requires-Dist: mkdocs-material
